pyqt_mac_buttons_widget/__init__.py
pyqt_mac_buttons_widget/macButtonsWidget.py
pyqt_mac_buttons_widget-0.0.15.dist-info/LICENSE
pyqt_mac_buttons_widget-0.0.15.dist-info/METADATA
pyqt_mac_buttons_widget-0.0.15.dist-info/WHEEL
pyqt_mac_buttons_widget-0.0.15.dist-info/top_level.txt
pyqt_mac_buttons_widget-0.0.15.dist-info/RECORD
