Metadata-Version: 2.1
Name: pyqt-mac-buttons-widget
Version: 0.0.15
Summary: PyQt macOS style of titlebar buttons (e.g. min/max/close) widget
Home-page: https://github.com/yjg30737/pyqt-mac-buttons-widget.git
Author: Jung Gyu Yoon
Author-email: yjg30737@gmail.com
License: MIT
Platform: UNKNOWN
License-File: LICENSE
Requires-Dist: PyQt5 (>=5.8)
Requires-Dist: pyqt-titlebar-buttons-widget (>=0.0.1)
